fourlabs_auth/__init__.py
fourlabs_auth/admin.py
fourlabs_auth/apps.py
fourlabs_auth/forms.py
fourlabs_auth/models.py
fourlabs_auth/urls.py
fourlabs_auth/views.py
fourlabs_auth/migrations/__init__.py
foursys_auth-0.1.6.dist-info/METADATA
foursys_auth-0.1.6.dist-info/WHEEL
foursys_auth-0.1.6.dist-info/top_level.txt
foursys_auth-0.1.6.dist-info/RECORD
