Metadata-Version: 2.4
Name: foursys-auth
Version: 0.1.6
Summary: Autenticação por email corporativo para Django
Author: Fourlabs
Author-email: fourlabs-un2@foursys.com.br
License: MIT
Classifier: Framework :: Django
Classifier: Programming Language :: Python :: 3
Classifier: License :: OSI Approved :: MIT License
Classifier: Operating System :: OS Independent
Requires-Python: >=3.8
Requires-Dist: Django>=5.2
Dynamic: author
Dynamic: author-email
Dynamic: classifier
Dynamic: description
Dynamic: description-content-type
Dynamic: license
Dynamic: requires-dist
Dynamic: requires-python
Dynamic: summary
